{
  "info": {
    "_postman_id": "9675bab1-a3dc-49ba-9736-651449473715",
    "name": "api-cartoon-generator",
    "schema": "https://schema.getpostman.com/json/collection/v2.1.0/collection.json",
    "_exporter_id": "40684984"
  },
  "item": [
    {
      "name": "UPLOAD-ASSETS",
      "request": {
        "method": "POST",
        "header": [],
        "body": {
          "mode": "formdata",
          "formdata": [
            {
              "key": "projectId",
              "value": "YJIsLkRX2dTYhvxqlb0e",
              "type": "text",
              "uuid": "25cec390-599d-4e37-9ae3-ca45c5e35767"
            },
            {
              "key": "characterId",
              "value": "FnnMqz9yFqIp9nsVr6pr",
              "type": "text",
              "uuid": "df72f72b-53d2-462a-b3b9-72d6c71412bd"
            },
            {
              "key": "file",
              "type": "file",
              "uuid": "ebf3c2c2-1203-4528-b327-e92cce5da76b",
              "src": "20260130_133841.jpg"
            }
          ]
        },
        "url": {
          "raw": "http://localhost:5001/ai-cartoon-generator-202-5d178/us-central1/upload_assets",
          "protocol": "http",
          "host": [
            "localhost"
          ],
          "port": "5001",
          "path": [
            "ai-cartoon-generator-202-5d178",
            "us-central1",
            "upload_assets"
          ]
        }
      },
      "response": []
    },
    {
      "name": "CREATE-PROJECT",
      "request": {
        "method": "POST",
        "header": [],
        "body": {
          "mode": "raw",
          "raw": "{\r\n  \"name\": \"Scary Granny's Kitchen\",\r\n  \"description\": \"A horror-themed cartoon featuring an unsettling grandmother.\"\r\n}",
          "options": {
            "raw": {
              "language": "json"
            }
          }
        },
        "url": {
          "raw": "http://localhost:5001/ai-cartoon-generator-202-5d178/us-central1/create_project",
          "protocol": "http",
          "host": [
            "localhost"
          ],
          "port": "5001",
          "path": [
            "ai-cartoon-generator-202-5d178",
            "us-central1",
            "create_project"
          ]
        }
      },
      "response": []
    },
    {
      "name": "CREATE-CHARACTER",
      "request": {
        "method": "POST",
        "header": [],
        "body": {
          "mode": "raw",
          "raw": "{\r\n  \"projectId\": \"YJIsLkRX2dTYhvxqlb0e\",\r\n  \"name\": \"Granny\",\r\n  \"description\": \"An unsettling, frail grandmother with a terrifyingly wide smile.\",\r\n  \"traits\": [\"Scary\", \"Raspy Voice\", \"Horror\"]\r\n}",
          "options": {
            "raw": {
              "language": "json"
            }
          }
        },
        "url": {
          "raw": "http://localhost:5001/ai-cartoon-generator-202-5d178/us-central1/create_character",
          "protocol": "http",
          "host": [
            "localhost"
          ],
          "port": "5001",
          "path": [
            "ai-cartoon-generator-202-5d178",
            "us-central1",
            "create_character"
          ]
        }
      },
      "response": []
    },
    {
      "name": "ANALYZE_SCRIPT",
      "request": {
        "method": "POST",
        "header": [],
        "body": {
          "mode": "raw",
          "raw": "{\r\n  \"projectId\": \"YJIsLkRX2dTYhvxqlb0e\",\r\n  \"scriptText\": \"INT. KITCHEN - NIGHT. The air is thick with the smell of burnt sugar. Granny stands at the counter, her back to the door. She is humming a warped version of a lullaby. YOUNG BOY enters, trembling. YOUNG BOY: Granny? I'm hungry. Granny turns slowly, her eyes milky white. GRANNY: Oh, I've been waiting for you, little one. The oven is just the right temperature.\"\r\n}",
          "options": {
            "raw": {
              "language": "json"
            }
          }
        },
        "url": {
          "raw": "http://localhost:5001/ai-cartoon-generator-202-5d178/us-central1/analyze_script",
          "protocol": "http",
          "host": [
            "localhost"
          ],
          "port": "5001",
          "path": [
            "ai-cartoon-generator-202-5d178",
            "us-central1",
            "analyze_script"
          ]
        }
      },
      "response": []
    },
    {
      "name": "GENERATE_FRAME",
      "request": {
        "method": "POST",
        "header": [],
        "body": {
          "mode": "raw",
          "raw": "{\r\n  \"projectId\": \"YJIsLkRX2dTYhvxqlb0e\",\r\n  \"sceneId\": \"b293c948-f9d6-47f6-86a9-3b1690c47d1e\"\r\n}",
          "options": {
            "raw": {
              "language": "json"
            }
          }
        },
        "url": {
          "raw": "http://localhost:5001/ai-cartoon-generator-202-5d178/us-central1/generate_frame",
          "protocol": "http",
          "host": [
            "localhost"
          ],
          "port": "5001",
          "path": [
            "ai-cartoon-generator-202-5d178",
            "us-central1",
            "generate_frame"
          ]
        }
      },
      "response": []
    }
  ]
}